misunderstanding/__init__.py
misunderstanding-0.0.1.dist-info/LICENSE
misunderstanding-0.0.1.dist-info/METADATA
misunderstanding-0.0.1.dist-info/WHEEL
misunderstanding-0.0.1.dist-info/top_level.txt
misunderstanding-0.0.1.dist-info/RECORD
