Metadata-Version: 2.1
Name: misunderstanding
Version: 0.0.1
Summary: Misunderstanding is a failure to understand something correctly.
Author-email: Alexander Fedotov <alex.fedotov@aol.com>
Project-URL: Homepage, https://github.com/multilogue/misunderstanding
Project-URL: Bug Tracker, https://github.com/multilogue/misunderstanding/issues
Classifier: Programming Language :: Python :: 3
Classifier: License :: OSI Approved :: MIT License
Classifier: Operating System :: OS Independent
Requires-Python: >=3.10
License-File: LICENSE
